CHANGELOG.md
COPYING
COPYING.fr
MANIFEST.in
README.md
setup.cfg
setup.py
test.ini
test_subclass.ini
ckanext/__init__.py
ckanext/scheming/__init__.py
ckanext/scheming/camel_photos.yaml
ckanext/scheming/ckan_dataset.yaml
ckanext/scheming/ckan_formpages.yaml
ckanext/scheming/codelist.json
ckanext/scheming/custom_group_with_status.json
ckanext/scheming/custom_org_with_address.json
ckanext/scheming/errors.py
ckanext/scheming/group_with_bookface.json
ckanext/scheming/helpers.py
ckanext/scheming/loader.py
ckanext/scheming/logic.py
ckanext/scheming/org_with_dept_id.json
ckanext/scheming/plugins.py
ckanext/scheming/presets.json
ckanext/scheming/subfields.yaml
ckanext/scheming/validation.py
ckanext/scheming/views.py
ckanext/scheming/2.8_templates/scheming/snippets/multiple_text_asset.html
ckanext/scheming/2.8_templates/scheming/snippets/scheming_asset.html
ckanext/scheming/2.8_templates/scheming/snippets/subfields_asset.html
ckanext/scheming/assets/resource.config
ckanext/scheming/assets/webassets.yml
ckanext/scheming/assets/js/scheming-multiple-text.js
ckanext/scheming/assets/js/scheming-repeating-subfields.js
ckanext/scheming/assets/styles/scheming.css
ckanext/scheming/templates/base.html
ckanext/scheming/templates/organization/edit_base.html
ckanext/scheming/templates/scheming/display_snippets/date.html
ckanext/scheming/templates/scheming/display_snippets/datetime.html
ckanext/scheming/templates/scheming/display_snippets/datetime_tz.html
ckanext/scheming/templates/scheming/display_snippets/email.html
ckanext/scheming/templates/scheming/display_snippets/file_size.html
ckanext/scheming/templates/scheming/display_snippets/json.html
ckanext/scheming/templates/scheming/display_snippets/link.html
ckanext/scheming/templates/scheming/display_snippets/markdown.html
ckanext/scheming/templates/scheming/display_snippets/multiple_choice.html
ckanext/scheming/templates/scheming/display_snippets/multiple_text.html
ckanext_scheming.egg-info/PKG-INFO
ckanext_scheming.egg-info/SOURCES.txt
ckanext_scheming.egg-info/dependency_links.txt
ckanext_scheming.egg-info/entry_points.txt
ckanext_scheming.egg-info/namespace_packages.txt
ckanext_scheming.egg-info/not-zip-safe
ckanext_scheming.egg-info/requires.txt
ckanext_scheming.egg-info/top_level.txt