Metadata-Version: 2.1
Name: ckanext-scheming
Version: 3.1.0
Summary: Easy, sharable custom CKAN schemas
Home-page: https://github.com/ckan/ckanext-scheming
Author: Ian Ward
Author-email: ian@excess.org
License: MIT
Keywords: ckan
Platform: UNKNOWN
License-File: COPYING
License-File: COPYING.fr
